LICENSE.txt
MANIFEST.in
README.rst
license.txt
setup.py
src/loge/__init__.py
src/loge/__main__.py
src/loge/development.txt
src/loge/license.txt
src/loge.egg-info/PKG-INFO
src/loge.egg-info/SOURCES.txt
src/loge.egg-info/dependency_links.txt
src/loge.egg-info/entry_points.txt
src/loge.egg-info/requires.txt
src/loge.egg-info/top_level.txt
src/loge/__pycache__/__init__.cpython-311.pyc
src/loge/__pycache__/__init__.cpython-312.pyc
src/loge/__pycache__/__init__.cpython-313.pyc
src/loge/__pycache__/__init__.cpython-39.pyc
src/loge/core/Core.py
src/loge/core/Script.py
src/loge/core/Shell.py
src/loge/core/__init__.py
src/loge/core/core_utils.py
src/loge/core/script_parsing.py
src/loge/core/shell_super_functions.py
src/loge/core/__pycache__/Core.cpython-311.pyc
src/loge/core/__pycache__/Core.cpython-312.pyc
src/loge/core/__pycache__/Core.cpython-313.pyc
src/loge/core/__pycache__/Core.cpython-39.pyc
src/loge/core/__pycache__/Script.cpython-311.pyc
src/loge/core/__pycache__/Script.cpython-312.pyc
src/loge/core/__pycache__/Script.cpython-313.pyc
src/loge/core/__pycache__/Script.cpython-39.pyc
src/loge/core/__pycache__/Shell.cpython-311.pyc
src/loge/core/__pycache__/Shell.cpython-312.pyc
src/loge/core/__pycache__/Shell.cpython-313.pyc
src/loge/core/__pycache__/Shell.cpython-39.pyc
src/loge/core/__pycache__/__init__.cpython-311.pyc
src/loge/core/__pycache__/__init__.cpython-312.pyc
src/loge/core/__pycache__/__init__.cpython-313.pyc
src/loge/core/__pycache__/__init__.cpython-39.pyc
src/loge/core/__pycache__/core_utils.cpython-311.pyc
src/loge/core/__pycache__/core_utils.cpython-312.pyc
src/loge/core/__pycache__/core_utils.cpython-313.pyc
src/loge/core/__pycache__/core_utils.cpython-39.pyc
src/loge/core/__pycache__/script_parsing.cpython-311.pyc
src/loge/core/__pycache__/script_parsing.cpython-312.pyc
src/loge/core/__pycache__/script_parsing.cpython-313.pyc
src/loge/core/__pycache__/script_parsing.cpython-39.pyc
src/loge/core/__pycache__/shell_super_functions.cpython-311.pyc
src/loge/core/__pycache__/shell_super_functions.cpython-312.pyc
src/loge/core/__pycache__/shell_super_functions.cpython-313.pyc
src/loge/core/__pycache__/shell_super_functions.cpython-39.pyc
