Metadata-Version: 2.2
Name: loge
Version: 0.3.5
Summary: Easy and fast dynamic report generation with Python3
Home-page: https://loge.readthedocs.io
Author: Lukasz Laba
Author-email: lukaszlaba@gmail.com
License: GNU General Public License (GPL)
Keywords: notebook,script,report
Classifier: Development Status :: 4 - Beta
Classifier: Environment :: X11 Applications :: Qt
Classifier: Intended Audience :: End Users/Desktop
Classifier: License :: OSI Approved :: GNU General Public License (GPL)
Classifier: Operating System :: POSIX :: Linux
Classifier: Operating System :: Microsoft :: Windows
Classifier: Programming Language :: Python
Classifier: Topic :: Scientific/Engineering
Requires-Python: >=3.5, <4
License-File: license.txt
Requires-Dist: pyqt5>=5.6
Requires-Dist: mistune==0.8.4
Requires-Dist: pillow
Dynamic: author
Dynamic: author-email
Dynamic: classifier
Dynamic: description
Dynamic: home-page
Dynamic: keywords
Dynamic: license
Dynamic: requires-dist
Dynamic: requires-python
Dynamic: summary
